LICENSE
MANIFEST.in
README.md
pyproject.toml
requirements.txt
setup.cfg
setup.py
torecsys/__init__.py
torecsys.egg-info/PKG-INFO
torecsys.egg-info/SOURCES.txt
torecsys.egg-info/dependency_links.txt
torecsys.egg-info/entry_points.txt
torecsys.egg-info/requires.txt
torecsys.egg-info/top_level.txt
torecsys/cli/__init__.py
torecsys/data/__init__.py
torecsys/data/sub_sampling.py
torecsys/data/dataloader/__init__.py
torecsys/data/dataloader/collate_fn.py
torecsys/data/dataloader/fields/__init__.py
torecsys/data/dataloader/fields/index_field.py
torecsys/data/dataloader/fields/sentence_field.py
torecsys/data/dataset/__init__.py
torecsys/data/dataset/dataset.py
torecsys/data/sample_data/__init__.py
torecsys/data/sample_data/download_data.py
torecsys/data/sample_data/load_data.py
torecsys/inputs/__init__.py
torecsys/inputs/inputs.py
torecsys/inputs/base/__init__.py
torecsys/inputs/base/concat_inputs.py
torecsys/inputs/base/image_inp.py
torecsys/inputs/base/list_indices_emb.py
torecsys/inputs/base/multi_indices_emb.py
torecsys/inputs/base/multi_indices_field_aware_emb.py
torecsys/inputs/base/pretrained_image_inp.py
torecsys/inputs/base/sequence_indices_emb.py
torecsys/inputs/base/single_index_emb.py
torecsys/inputs/base/stacked_inp.py
torecsys/inputs/base/value_inp.py
torecsys/layers/__init__.py
torecsys/layers/regularization.py
torecsys/layers/ctr/__init__.py
torecsys/layers/ctr/attentional_factorization_machine.py
torecsys/layers/ctr/bias_encoding.py
torecsys/layers/ctr/bilinear.py
torecsys/layers/ctr/bilinear_interaction.py
torecsys/layers/ctr/compose_excitation_network.py
torecsys/layers/ctr/compress_interaction_network.py
torecsys/layers/ctr/cross_network.py
torecsys/layers/ctr/dynamic_routing.py
torecsys/layers/ctr/factorization_machine.py
torecsys/layers/ctr/field_aware_factorization_machine.py
torecsys/layers/ctr/inner_product_network.py
torecsys/layers/ctr/mixture_of_experts.py
torecsys/layers/ctr/multilayer_perceptron.py
torecsys/layers/ctr/outer_product_network.py
torecsys/layers/ctr/position_embedding.py
torecsys/layers/ctr/positon_bias_aware_learning_framework.py
torecsys/layers/ctr/wide.py
torecsys/layers/emb/__init__.py
