Metadata-Version: 2.1
Name: torecsys
Version: 0.0.1.dev2
Summary: ToR[e]cSys is a PyTorch Framework to implement recommendation system algorithms, including but not limited to click-through-rate (CTR) prediction, learning-to-ranking (LTR), and Matrix/Tensor Embedding. The project objective is to develop a ecosystem to experiment, share, reproduce, and deploy in real world in a smooth and easy way.
Home-page: https://github.com/p768lwy3/torecsys
Author: Jasper Li
Author-email: jasper_liwaiyin@protonmail.com
License: MIT
Project-URL: Bug Tracker, https://github.com/p768lwy3/torecsys/issues
Project-URL: Documentation, https://torecsys.readthedocs.io/en/latest/
Project-URL: Source, https://github.com/p768lwy3/torecsys
Keywords: recsys recommendersystem recommendationsystem machinelearning deeplearning research ctr clickthroughrate
Platform: UNKNOWN
Classifier: Development Status :: 1 - Planning
Classifier: Intended Audience :: Science/Research
Classifier: Topic :: Scientific/Engineering :: Artificial Intelligence
Classifier: Programming Language :: Python :: 3
Classifier: Programming Language :: Python :: 3.8
Classifier: Programming Language :: Python :: 3.9
Classifier: License :: OSI Approved :: MIT License
Classifier: Operating System :: OS Independent
Requires-Python: >=3.8
License-File: LICENSE
